lldap/__init__.py
lldap/client.py
lldap/config.py
lldap/exceptions.py
lldap/groups.py
lldap/models.py
lldap/users.py
lldap_py-0.1.0.dist-info/licenses/LICENSE
lldap_py-0.1.0.dist-info/METADATA
lldap_py-0.1.0.dist-info/WHEEL
lldap_py-0.1.0.dist-info/top_level.txt
lldap_py-0.1.0.dist-info/RECORD
