Metadata-Version: 2.4
Name: lldap-py
Version: 0.1.0
Summary: Python tool for managing LLDAP servers
Home-page: https://github.com/luca2618/lldap-py
Author: Lucas Sylvester
Classifier: Development Status :: 3 - Alpha
Classifier: Intended Audience :: System Administrators
Classifier: Topic :: System :: Systems Administration :: Authentication/Directory :: LDAP
Classifier: License :: OSI Approved :: MIT License
Classifier: Programming Language :: Python :: 3
Requires-Python: >=3.8
License-File: LICENSE
Requires-Dist: requests>=2.28.0
Requires-Dist: toml>=0.10.2
Requires-Dist: click>=8.0.0
Requires-Dist: ldap3>=2.9.0
Provides-Extra: test
Requires-Dist: pytest; extra == "test"
Dynamic: author
Dynamic: classifier
Dynamic: description
Dynamic: description-content-type
Dynamic: home-page
Dynamic: license-file
Dynamic: provides-extra
Dynamic: requires-dist
Dynamic: requires-python
Dynamic: summary
